Metadata-Version: 1.1
Name: arkgamepy
Version: 0.1.2
Summary: A library for reading and writing the file formats of ARK: Survival Evolved
Home-page: https://github.com/DerekRies/arkpy
Author: Derek Ries
Author-email: iamderekries@gmail.com
License: MIT
Keywords: ark,game,ark survival,ark survival evolved,.ark,.arkprofile,.arktribe,.arkcharactersetting,reverse engineering,game files
Platform: UNKNOWN
Classifier: Development Status :: 3 - Alpha
Classifier: Intended Audience :: Developers
Classifier: Topic :: Software Development :: Libraries
Classifier: License :: OSI Approved :: MIT License
Classifier: Programming Language :: Python :: 2.6
Classifier: Programming Language :: Python :: 2.7
